{
  "version": "v4",
  "repo": "DefinitelyTyped/DefinitelyTyped",
  "ref": "master",
  "path": "typings",
  "bundle": "typings/tsd.d.ts",
  "installed": {
    "github-electron/github-electron.d.ts": {
      "commit": "220716d99a77df1654fb4f6cd760dc134ffa8e89"
    },
    "node/node.d.ts": {
      "commit": "220716d99a77df1654fb4f6cd760dc134ffa8e89"
    },
    "page/page.d.ts": {
      "commit": "220716d99a77df1654fb4f6cd760dc134ffa8e89"
    },
    "minimist/minimist.d.ts": {
      "commit": "220716d99a77df1654fb4f6cd760dc134ffa8e89"
    }
  }
}